test.py
cptf/__init__.py
cptf/errors.py
CaptionedFileFormat-1.1.0.dist-info/METADATA
CaptionedFileFormat-1.1.0.dist-info/WHEEL
CaptionedFileFormat-1.1.0.dist-info/top_level.txt
CaptionedFileFormat-1.1.0.dist-info/RECORD
