Metadata-Version: 2.1
Name: CaptionedFileFormat
Version: 1.1.0
Summary: A Python wrapper for the Captioned File (CPTF) file format
Author: Oakchris1955
Project-URL: Homepage, https://github.com/Oakchris1955/Captioned-File
Project-URL: Bug Tracker, https://github.com/Oakchris1955/Captioned-File/issues
Classifier: Programming Language :: Python :: 3
Classifier: License :: OSI Approved :: MIT License
Classifier: Operating System :: OS Independent
Requires-Python: >=3.7
